sma2ldif.py
sma2ldif-0.0.8.dist-info/licenses/LICENSE
sma2ldif-0.0.8.dist-info/METADATA
sma2ldif-0.0.8.dist-info/WHEEL
sma2ldif-0.0.8.dist-info/entry_points.txt
sma2ldif-0.0.8.dist-info/top_level.txt
sma2ldif-0.0.8.dist-info/RECORD
