Metadata-Version: 2.4
Name: sma2ldif
Version: 0.0.8
Summary: Tool to Convert Sendmail Alias Files to Proofpoint LDIF Format
License: MIT
Project-URL: repository, https://github.com/pfptcommunity/sma2ldif
Requires-Python: >3.9
License-File: LICENSE
Dynamic: license-file
